[
    {
        "card_name": "MZ11 \u2014 Elesh Norn, Essence Cenobite",
        "number": 20,
        "shape": "normal",
        "set": "FOOD",
        "position": ""
    },
    {
        "card_name": "MZ12 \u2014 Zimone, Galeforce Researcher",
        "number": 53,
        "shape": "normal",
        "set": "FOOD",
        "position": ""
    },
    {
        "card_name": "MZ13 \u2014 Rankle, Trusted Borrower",
        "number": 89,
        "shape": "normal",
        "set": "FOOD",
        "position": ""
    },
    {
        "card_name": "MZ14 \u2014 Mabel, Valley's Champion",
        "number": 122,
        "shape": "normal",
        "set": "FOOD",
        "position": ""
    },
    {
        "card_name": "MZ15 \u2014 Umori, Glue Beast",
        "number": 157,
        "shape": "normal",
        "set": "FOOD",
        "position": ""
    },
    {
        "card_name": "RW01 \u2014 Mondrak, Impassable Horror",
        "number": 21,
        "shape": "normal",
        "set": "FOOD",
        "position": ""
    },
    {
        "card_name": "RU01 \u2014 Larine Arneza, Valedictorian",
        "number": 54,
        "shape": "normal",
        "set": "FOOD",
        "position": ""
    },
    {
        "card_name": "RB01 \u2014 Agatha, Cauldron Witch",
        "number": 90,
        "shape": "normal",
        "set": "FOOD",
        "position": ""
    },
    {
        "card_name": "RR01 \u2014 Whisker, the Fearless",
        "number": 124,
        "shape": "normal",
        "set": "FOOD",
        "position": ""
    },
    {
        "card_name": "RG01 \u2014 Kogla, the Titan Appe",
        "number": 158,
        "shape": "normal",
        "set": "FOOD",
        "position": ""
    },
    {
        "card_name": "RW02 \u2014 Flavor of Orthodoxy",
        "number": 22,
        "shape": "normal",
        "set": "FOOD",
        "position": ""
    },
    {
        "card_name": "RU02 \u2014 Pensive Professor",
        "number": 55,
        "shape": "normal",
        "set": "FOOD",
        "position": ""
    },
    {
        "card_name": "RB02 \u2014 Gumdrop Poisoner",
        "number": 91,
        "shape": "adventure",
        "set": "FOOD",
        "position": ""
    },
    {
        "card_name": "RR02 \u2014 Sunspine Lynx",
        "number": 125,
        "shape": "normal",
        "set": "FOOD",
        "position": ""
    },
    {
        "card_name": "RG02 \u2014 WildCat Bonder",
        "number": 159,
        "shape": "normal",
        "set": "FOOD",
        "position": ""
    },
    {
        "card_name": "RW03 \u2014 Mite Overseer",
        "number": 23,
        "shape": "normal",
        "set": "FOOD",
        "position": ""
    },
    {
        "card_name": "RU03 \u2014 Cosmophysicist",
        "number": 56,
        "shape": "normal",
        "set": "FOOD",
        "position": ""
    },
    {
        "card_name": "RB03 \u2014 Magic Piggies",
        "number": 92,
        "shape": "normal",
        "set": "FOOD",
        "position": ""
    },
    {
        "card_name": "RR03 \u2014 Sword from the Pond",
        "number": 126,
        "shape": "normal",
        "set": "FOOD",
        "position": ""
    },
    {
        "card_name": "RG03 \u2014 Umori's Hunger",
        "number": 160,
        "shape": "normal",
        "set": "FOOD",
        "position": ""
    },
    {
        "card_name": "RW04 \u2014 Begin the Feast",
        "number": 24,
        "shape": "normal",
        "set": "FOOD",
        "position": ""
    },
    {
        "card_name": "RU04 \u2014 Chronicle",
        "number": 57,
        "shape": "normal",
        "set": "FOOD",
        "position": ""
    },
    {
        "card_name": "RB04 \u2014 Careful What You Ask For",
        "number": 93,
        "shape": "normal",
        "set": "FOOD",
        "position": ""
    },
    {
        "card_name": "RR04 \u2014 Flavor of Autumn",
        "number": 127,
        "shape": "normal",
        "set": "FOOD",
        "position": ""
    },
    {
        "card_name": "RG04 \u2014 Biomewide Migration",
        "number": 161,
        "shape": "normal",
        "set": "FOOD",
        "position": ""
    },
    {
        "card_name": "CW01 \u2014 Phyrexian Pridemate",
        "number": 2,
        "shape": "normal",
        "set": "FOOD",
        "position": ""
    },
    {
        "card_name": "RZ07 \u2014 Reason",
        "number": 58,
        "shape": "aftermath",
        "set": "FOOD",
        "position": ""
    },
    {
        "card_name": "CB01 \u2014 Plague Knight",
        "number": 71,
        "shape": "normal",
        "set": "FOOD",
        "position": ""
    },
    {
        "card_name": "CR01 \u2014 Raging Marten",
        "number": 104,
        "shape": "normal",
        "set": "FOOD",
        "position": ""
    },
    {
        "card_name": "CG01 \u2014 Hungry Brushwagg",
        "number": 139,
        "shape": "normal",
        "set": "FOOD",
        "position": ""
    },
    {
        "card_name": "CW02 \u2014 Bladed Ambassador",
        "number": 3,
        "shape": "normal",
        "set": "FOOD",
        "position": ""
    },
    {
        "card_name": "CU01 \u2014 Quandrix Garden Gate",
        "number": 35,
        "shape": "normal",
        "set": "FOOD",
        "position": ""
    },
    {
        "card_name": "CB02 \u2014 Midnight Snacqueraider",
        "number": 72,
        "shape": "adventure",
        "set": "FOOD",
        "position": ""
    },
    {
        "card_name": "CR02 \u2014 Pilfering Vole",
        "number": 105,
        "shape": "adventure",
        "set": "FOOD",
        "position": ""
    },
    {
        "card_name": "CG02 \u2014 Thornvault Anomaly",
        "number": 140,
        "shape": "normal",
        "set": "FOOD",
        "position": ""
    },
    {
        "card_name": "CW03 \u2014 Autocatalytic Hare",
        "number": 4,
        "shape": "normal",
        "set": "FOOD",
        "position": ""
    },
    {
        "card_name": "CU02 \u2014 Arithmetic Frogression",
        "number": 36,
        "shape": "normal",
        "set": "FOOD",
        "position": ""
    },
    {
        "card_name": "CB03 \u2014 Mellow-o-Wisps",
        "number": 73,
        "shape": "normal",
        "set": "FOOD",
        "position": ""
    },
    {
        "card_name": "CR03 \u2014 Emberheart Mouster",
        "number": 106,
        "shape": "normal",
        "set": "FOOD",
        "position": ""
    },
    {
        "card_name": "CG03 \u2014 Symbiotic Shaman",
        "number": 141,
        "shape": "normal",
        "set": "FOOD",
        "position": ""
    },
    {
        "card_name": "CW04 \u2014 Celestial Crier",
        "number": 5,
        "shape": "normal",
        "set": "FOOD",
        "position": ""
    },
    {
        "card_name": "CU03 \u2014 Quaildratic Formula",
        "number": 37,
        "shape": "normal",
        "set": "FOOD",
        "position": ""
    },
    {
        "card_name": "CB04 \u2014 Oilsworn Paladin",
        "number": 74,
        "shape": "normal",
        "set": "FOOD",
        "position": ""
    },
    {
        "card_name": "CR04 \u2014 Sharp Clawed Scout",
        "number": 107,
        "shape": "normal",
        "set": "FOOD",
        "position": ""
    },
    {
        "card_name": "CG04 \u2014 Webbonder",
        "number": 142,
        "shape": "normal",
        "set": "FOOD",
        "position": ""
    },
    {
        "card_name": "CW05 \u2014 Elder Cenobite",
        "number": 6,
        "shape": "normal",
        "set": "FOOD",
        "position": ""
    },
    {
        "card_name": "CU04 \u2014 Sneaky Researcher",
        "number": 38,
        "shape": "normal",
        "set": "FOOD",
        "position": ""
    },
    {
        "card_name": "CB05 \u2014 Innocuous Prankster",
        "number": 75,
        "shape": "normal",
        "set": "FOOD",
        "position": ""
    },
    {
        "card_name": "CR05 \u2014 Owl-Eyed Archer",
        "number": 108,
        "shape": "normal",
        "set": "FOOD",
        "position": ""
    },
    {
        "card_name": "CG05 \u2014 Beetle-Horned Rhino",
        "number": 143,
        "shape": "normal",
        "set": "FOOD",
        "position": ""
    },
    {
        "card_name": "CW06 \u2014 Lorehold Paleodietitian",
        "number": 7,
        "shape": "normal",
        "set": "FOOD",
        "position": ""
    },
    {
        "card_name": "CU05 \u2014 Professor of Culinary Arts",
        "number": 39,
        "shape": "normal",
        "set": "FOOD",
        "position": ""
    },
    {
        "card_name": "CB06 \u2014 The Tooth Faerie",
        "number": 76,
        "shape": "normal",
        "set": "FOOD",
        "position": ""
    },
    {
        "card_name": "CR06 \u2014Shrunken Field Reasearcher",
        "number": 109,
        "shape": "normal",
        "set": "FOOD",
        "position": ""
    },
    {
        "card_name": "CG06 \u2014 Zagoth Snapper",
        "number": 144,
        "shape": "normal",
        "set": "FOOD",
        "position": ""
    },
    {
        "card_name": "CW07 \u2014 Devote Evangelist",
        "number": 8,
        "shape": "normal",
        "set": "FOOD",
        "position": ""
    },
    {
        "card_name": "CU06 \u2014 Exponentiation Professor",
        "number": 40,
        "shape": "adventure",
        "set": "FOOD",
        "position": ""
    },
    {
        "card_name": "CB07 \u2014 Professor From Another Realm",
        "number": 77,
        "shape": "adventure",
        "set": "FOOD",
        "position": ""
    },
    {
        "card_name": "CR07 \u2014 Burning Oak Duo",
        "number": 110,
        "shape": "normal",
        "set": "FOOD",
        "position": ""
    },
    {
        "card_name": "CG07 \u2014 Megafauna Grazer",
        "number": 145,
        "shape": "normal",
        "set": "FOOD",
        "position": ""
    },
    {
        "card_name": "CW08 \u2014 Sleeperagent Skymount",
        "number": 9,
        "shape": "normal",
        "set": "FOOD",
        "position": ""
    },
    {
        "card_name": "CU07 \u2014 Missing Ingredient",
        "number": 41,
        "shape": "normal",
        "set": "FOOD",
        "position": ""
    },
    {
        "card_name": "CB08 \u2014 Big Bad Ouphe",
        "number": 78,
        "shape": "normal",
        "set": "FOOD",
        "position": ""
    },
    {
        "card_name": "CR08 \u2014 Three Tree City Guard",
        "number": 111,
        "shape": "normal",
        "set": "FOOD",
        "position": ""
    },
    {
        "card_name": "CG08 \u2014 Indatha Ooze",
        "number": 146,
        "shape": "normal",
        "set": "FOOD",
        "position": ""
    },
    {
        "card_name": "CW09 \u2014 Preator's Glory",
        "number": 10,
        "shape": "normal",
        "set": "FOOD",
        "position": ""
    },
    {
        "card_name": "CU08 \u2014 Check your work!",
        "number": 42,
        "shape": "normal",
        "set": "FOOD",
        "position": ""
    },
    {
        "card_name": "CB09 \u2014 Shadow Swap",
        "number": 79,
        "shape": "normal",
        "set": "FOOD",
        "position": ""
    },
    {
        "card_name": "CR09 \u2014 Oilslick Watchfrog",
        "number": 112,
        "shape": "normal",
        "set": "FOOD",
        "position": ""
    },
    {
        "card_name": "CG09 \u2014 Reynard Bonder",
        "number": 147,
        "shape": "adventure",
        "set": "FOOD",
        "position": ""
    },
    {
        "card_name": "CW10 \u2014 Served In Ice",
        "number": 11,
        "shape": "normal",
        "set": "FOOD",
        "position": ""
    },
    {
        "card_name": "CU09 \u2014 Re-Hash",
        "number": 43,
        "shape": "normal",
        "set": "FOOD",
        "position": ""
    },
    {
        "card_name": "CB10 \u2014 Delicious Apples",
        "number": 80,
        "shape": "normal",
        "set": "FOOD",
        "position": ""
    },
    {
        "card_name": "CR10 \u2014 Pond Creek Predator",
        "number": 113,
        "shape": "normal",
        "set": "FOOD",
        "position": ""
    },
    {
        "card_name": "CG10 \u2014 Hungry Pinekraken",
        "number": 148,
        "shape": "normal",
        "set": "FOOD",
        "position": ""
    },
    {
        "card_name": "CW11 \u2014 Hunger of Mites",
        "number": 12,
        "shape": "normal",
        "set": "FOOD",
        "position": ""
    },
    {
        "card_name": "CU10 \u2014 Freshman Meal Plan",
        "number": 44,
        "shape": "normal",
        "set": "FOOD",
        "position": ""
    },
    {
        "card_name": "CB11 \u2014 Negotiated Death",
        "number": 81,
        "shape": "normal",
        "set": "FOOD",
        "position": ""
    },
    {
        "card_name": "CR11 \u2014 Uplift Animalfolk",
        "number": 114,
        "shape": "normal",
        "set": "FOOD",
        "position": ""
    },
    {
        "card_name": "CG11 \u2014 Advantageous Adaptation",
        "number": 149,
        "shape": "normal",
        "set": "FOOD",
        "position": ""
    },
    {
        "card_name": "CW12 \u2014 Phyrexian Chalice",
        "number": 13,
        "shape": "normal",
        "set": "FOOD",
        "position": ""
    },
    {
        "card_name": "CU11 \u2014 Publish Analysis",
        "number": 45,
        "shape": "normal",
        "set": "FOOD",
        "position": ""
    },
    {
        "card_name": "CB12 \u2014 Baked into a Pie",
        "number": 82,
        "shape": "normal",
        "set": "FOOD",
        "position": ""
    },
    {
        "card_name": "CR12 \u2014 Fling a Pie",
        "number": 115,
        "shape": "normal",
        "set": "FOOD",
        "position": ""
    },
    {
        "card_name": "CG11 \u2014 Devour Whole",
        "number": 150,
        "shape": "normal",
        "set": "FOOD",
        "position": ""
    },
    {
        "card_name": "CW13 \u2014 Open Wide",
        "number": 14,
        "shape": "normal",
        "set": "FOOD",
        "position": ""
    },
    {
        "card_name": "CU12 \u2014 Call Campus Saftey",
        "number": 46,
        "shape": "normal",
        "set": "FOOD",
        "position": ""
    },
    {
        "card_name": "CB13 \u2014 I'm Eternally Grateful",
        "number": 83,
        "shape": "normal",
        "set": "FOOD",
        "position": ""
    },
    {
        "card_name": "CR13 \u2014 Rally the Squirrels",
        "number": 116,
        "shape": "normal",
        "set": "FOOD",
        "position": ""
    },
    {
        "card_name": "CG13\u2014 Surivor's Bond",
        "number": 151,
        "shape": "normal",
        "set": "FOOD",
        "position": ""
    },
    {
        "card_name": "CW14 \u2014 Oleaginous Portal",
        "number": 15,
        "shape": "normal",
        "set": "FOOD",
        "position": ""
    },
    {
        "card_name": "CU13 \u2014 Inspiring Lemma Beans",
        "number": 47,
        "shape": "normal",
        "set": "FOOD",
        "position": ""
    },
    {
        "card_name": "CB14 \u2014 Entreating Witch",
        "number": 84,
        "shape": "normal",
        "set": "FOOD",
        "position": ""
    },
    {
        "card_name": "CR14 \u2014 Wield the Seed Flame",
        "number": 117,
        "shape": "normal",
        "set": "FOOD",
        "position": ""
    },
    {
        "card_name": "CG14 \u2014 Thunderous Stomp",
        "number": 152,
        "shape": "normal",
        "set": "FOOD",
        "position": ""
    },
    {
        "card_name": "CW15a \u2014 Trial of Faith",
        "number": 16,
        "shape": "battle split",
        "set": "FOOD",
        "position": ""
    },
    {
        "card_name": "CU14 \u2014 Group Study",
        "number": 48,
        "shape": "normal",
        "set": "FOOD",
        "position": ""
    },
    {
        "card_name": "CB15a \u2014 Trial of Guile",
        "number": 85,
        "shape": "battle split",
        "set": "FOOD",
        "position": ""
    },
    {
        "card_name": "CR15a \u2014 Trial of Scurry",
        "number": 118,
        "shape": "battle split",
        "set": "FOOD",
        "position": ""
    },
    {
        "card_name": "CG15a \u2014 Trial of Might",
        "number": 153,
        "shape": "battle split",
        "set": "FOOD",
        "position": ""
    },
    {
        "card_name": "CW15b \u2014 Lifeforce Alliance",
        "number": 17,
        "shape": "battle split",
        "set": "FOOD",
        "position": ""
    },
    {
        "card_name": "CU15a \u2014 Test of Intellect",
        "number": 49,
        "shape": "battle split",
        "set": "FOOD",
        "position": ""
    },
    {
        "card_name": "CB15b \u2014 Fruitful Alliance",
        "number": 86,
        "shape": "battle split",
        "set": "FOOD",
        "position": ""
    },
    {
        "card_name": "CR15b \u2014 Battleproven Duo",
        "number": 119,
        "shape": "battle split",
        "set": "FOOD",
        "position": ""
    },
    {
        "card_name": "CG15b \u2014 Kinship of the Herd",
        "number": 154,
        "shape": "battle split",
        "set": "FOOD",
        "position": ""
    },
    {
        "card_name": "CW16a \u2014 Raid on the Fifth Sphere",
        "number": 18,
        "shape": "battle split",
        "set": "FOOD",
        "position": ""
    },
    {
        "card_name": "CU15b \u2014 Collaborative Scholarship",
        "number": 50,
        "shape": "battle split",
        "set": "FOOD",
        "position": ""
    },
    {
        "card_name": "CB16a \u2014 Raid on the Fairie Garden",
        "number": 87,
        "shape": "battle split",
        "set": "FOOD",
        "position": ""
    },
    {
        "card_name": "CR16a \u2014 Raid on Emberheart-Oven",
        "number": 120,
        "shape": "battle split",
        "set": "FOOD",
        "position": ""
    },
    {
        "card_name": "CG16a \u2014 Raid on Ketria Gemgrove",
        "number": 155,
        "shape": "battle split",
        "set": "FOOD",
        "position": ""
    },
    {
        "card_name": "CW16b \u2014 Mother's Retribution",
        "number": 19,
        "shape": "normal",
        "set": "FOOD",
        "position": ""
    },
    {
        "card_name": "CU16a \u2014 Raid on the Potions Class",
        "number": 51,
        "shape": "battle split",
        "set": "FOOD",
        "position": ""
    },
    {
        "card_name": "CB16b \u2014 Rankle's Reveal",
        "number": 88,
        "shape": "normal",
        "set": "FOOD",
        "position": ""
    },
    {
        "card_name": "CR16b \u2014 Mabel's Rise",
        "number": 121,
        "shape": "normal",
        "set": "FOOD",
        "position": ""
    },
    {
        "card_name": "CG16b \u2014 Umori Snaps Back",
        "number": 156,
        "shape": "normal",
        "set": "FOOD",
        "position": ""
    },
    {
        "card_name": "e"
    },
    {
        "card_name": "CU16b \u2014 Zimone Gets Even",
        "number": 52,
        "shape": "normal",
        "set": "FOOD",
        "position": ""
    },
    {
        "card_name": "e"
    },
    {
        "card_name": "e"
    },
    {
        "card_name": "e"
    },
    {
        "card_name": "er"
    },
    {
        "card_name": "er"
    },
    {
        "card_name": "er"
    },
    {
        "card_name": "er"
    },
    "a->gold",
    {
        "card_name": "M02 \u2014 Ms. Bumbleflower, Generous Hare",
        "number": 176,
        "shape": "transform double faced",
        "set": "FOOD",
        "position": ""
    },
    {
        "card_name": "M03 \u2014 Gyruda, Oscilating Wave",
        "number": 177,
        "shape": "transform double faced",
        "set": "FOOD",
        "position": ""
    },
    {
        "card_name": "M04 \u2014 Cruelclaw, Leader of the Red Scarves",
        "number": 178,
        "shape": "transform double faced",
        "set": "FOOD",
        "position": ""
    },
    {
        "card_name": "M05 \u2014 Kaheera, Monster Paragon",
        "number": 179,
        "shape": "transform double faced",
        "set": "FOOD",
        "position": ""
    },
    {
        "card_name": "M01 \u2014 Ixhel, Porcelain Angel",
        "number": 175,
        "shape": "transform double faced",
        "set": "FOOD",
        "position": ""
    },
    {
        "card_name": "RZ01 \u2014 Holy Relics Masterclass",
        "number": 185,
        "shape": "class",
        "set": "FOOD",
        "position": ""
    },
    {
        "card_name": "RZ05 -- May I Have Your Name",
        "number": 189,
        "shape": "normal",
        "set": "FOOD",
        "position": ""
    },
    {
        "card_name": "RZ08 \u2014 Sand Witch",
        "number": 191,
        "shape": "normal",
        "set": "FOOD",
        "position": ""
    },
    {
        "card_name": "RZ10 \u2014 Find the Magic Acorn",
        "number": 193,
        "shape": "normal",
        "set": "FOOD",
        "position": ""
    },
    {
        "card_name": "RZ04 \u2014 Wormcoil Hydra",
        "number": 188,
        "shape": "normal",
        "set": "FOOD",
        "position": ""
    },
    {
        "card_name": "CZ01 \u2014 Biblopex Caterer",
        "number": 227,
        "shape": "normal",
        "set": "FOOD",
        "position": ""
    },
    {
        "card_name": "CZ05 \u2014 Entrancing Faye",
        "number": 231,
        "shape": "adventure",
        "set": "FOOD",
        "position": ""
    },
    {
        "card_name": "CZ08 \u2014 Haymeadow Brigand",
        "number": 234,
        "shape": "normal",
        "set": "FOOD",
        "position": ""
    },
    {
        "card_name": "CZ10 \u2014 Frenzied Bonder",
        "number": 236,
        "shape": "normal",
        "set": "FOOD",
        "position": ""
    },
    {
        "card_name": "CZ04 \u2014 OilFang Bonder",
        "number": 230,
        "shape": "normal",
        "set": "FOOD",
        "position": ""
    },
    {
        "card_name": "er"
    },
    {
        "card_name": "er"
    },
    {
        "card_name": "er"
    },
    {
        "card_name": "er"
    },
    {
        "card_name": "er"
    },
    {
        "card_name": "M08 \u2014 Eriette of Love's Bite",
        "number": 182,
        "shape": "transform double faced",
        "set": "FOOD",
        "position": ""
    },
    {
        "card_name": "RZ06 \u2014 Advanced Bravery",
        "number": 190,
        "shape": "class",
        "set": "FOOD",
        "position": ""
    },
    {
        "card_name": "RZ09 \u2014 Esdragon",
        "number": 192,
        "shape": "normal",
        "set": "FOOD",
        "position": ""
    },
    {
        "card_name": "M06 \u2014 Urabrask, Rebel Praetor",
        "number": 180,
        "shape": "transform double faced",
        "set": "FOOD",
        "position": ""
    },
    {
        "card_name": "M07 \u2014 Quandrix, Resonance Maestro",
        "number": 181,
        "shape": "transform double faced",
        "set": "FOOD",
        "position": ""
    },
    {
        "card_name": "RZ02 \u2014 Duskhunter Bat",
        "number": 186,
        "shape": "normal",
        "set": "FOOD",
        "position": ""
    },
    {
        "card_name": "CZ06 \u2014 Hydrodynamicist",
        "number": 232,
        "shape": "normal",
        "set": "FOOD",
        "position": ""
    },
    {
        "card_name": "CZ09 \u2014 Stag Bonder",
        "number": 235,
        "shape": "normal",
        "set": "FOOD",
        "position": ""
    },
    {
        "card_name": "M09 \u2014 Quintorious, Defender of History",
        "number": 183,
        "shape": "transform double faced",
        "set": "FOOD",
        "position": ""
    },
    {
        "card_name": "M10 - The Golden Goose",
        "number": 184,
        "shape": "transform double faced",
        "set": "FOOD",
        "position": ""
    },
    {
        "card_name": "CZ02 \u2014 Liturgy Preparer",
        "number": 228,
        "shape": "normal",
        "set": "FOOD",
        "position": ""
    },
    {
        "card_name": "e"
    },
    {
        "card_name": "e"
    },
    {
        "card_name": "RZ03 \u2014 Blight Rabbit",
        "number": 187,
        "shape": "normal",
        "set": "FOOD",
        "position": ""
    },
    {
        "card_name": "CZ07 \u2014 Strix Bonder",
        "number": 233,
        "shape": "normal",
        "set": "FOOD",
        "position": ""
    },
    {
        "card_name": "e"
    },
    {
        "card_name": "e"
    },
    {
        "card_name": "e"
    },
    {
        "card_name": "CZ03 \u2014 Consummate Bladetail",
        "number": 229,
        "shape": "normal",
        "set": "FOOD",
        "position": ""
    },
    {
        "card_name": "e"
    },
    {
        "card_name": "er"
    },
    {
        "card_name": "er"
    },
    {
        "card_name": "er"
    },
    {
        "card_name": "er"
    },
    "a->colorless",
    {
        "card_name": "RL02 \u2014 Atollpology",
        "number": 262,
        "shape": "class",
        "set": "FOOD",
        "position": ""
    },
    {
        "card_name": "CA01 \u2014 Egg BombBomb",
        "number": 240,
        "shape": "normal",
        "set": "FOOD",
        "position": ""
    },
    {
        "card_name": "CA02 \u2014",
        "number": 241,
        "shape": "normal",
        "set": "FOOD",
        "position": ""
    },
    {
        "card_name": "CA03 \u2014 Cabbatrice",
        "number": 242,
        "shape": "normal",
        "set": "FOOD",
        "position": ""
    },
    {
        "card_name": "CA04 \u2014 Ginger Snaposaurus",
        "number": 243,
        "shape": "normal",
        "set": "FOOD",
        "position": ""
    },
    {
        "card_name": "er"
    },
    {
        "card_name": "er"
    },
    {
        "card_name": "er"
    },
    {
        "card_name": "er"
    },
    "a->land",
    {
        "card_name": "RL01 \u2014 The Holy Oil Spring",
        "number": 261,
        "shape": "normal",
        "set": "FOOD",
        "position": ""
    },
    {
        "card_name": "CL07 \u2014 Bilbelopex",
        "number": 257,
        "shape": "normal",
        "set": "FOOD",
        "position": ""
    },
    {
        "card_name": "RL03 \u2014 The Dusk Woods",
        "number": 263,
        "shape": "transform double faced",
        "set": "FOOD",
        "position": ""
    },
    {
        "card_name": "RL04 \u2014 Emberheart Greatsword",
        "number": 123,
        "shape": "normal",
        "set": "FOOD",
        "position": ""
    },
    {
        "card_name": "RL05 \u2014 Living Great Tree",
        "number": 162,
        "shape": "normal",
        "set": "FOOD",
        "position": ""
    },
    {
        "card_name": "CL06 \u2014 Norn's Basilica",
        "number": 256,
        "shape": "normal",
        "set": "FOOD",
        "position": ""
    },
    {
        "card_name": "e"
    },
    {
        "card_name": "CL08 \u2014 Witches Hut",
        "number": 258,
        "shape": "normal",
        "set": "FOOD",
        "position": ""
    },
    {
        "card_name": "CL09 \u2014 The Valley",
        "number": 259,
        "shape": "normal",
        "set": "FOOD",
        "position": ""
    },
    {
        "card_name": "CL10 \u2014 Ketria",
        "number": 260,
        "shape": "normal",
        "set": "FOOD",
        "position": ""
    },
    {
        "card_name": "er"
    },
    {
        "card_name": "er"
    },
    {
        "card_name": "er"
    },
    {
        "card_name": "er"
    },
    {
        "card_name": "er"
    },
    {
        "card_name": "CL01 \u2014 Raugrin Lavaflats",
        "number": 251,
        "shape": "normal",
        "set": "FOOD",
        "position": ""
    },
    {
        "card_name": "CL02 \u2014 The Woods at Twilight",
        "number": 252,
        "shape": "normal",
        "set": "FOOD",
        "position": ""
    },
    {
        "card_name": "CL03 \u2014 Department of Environmental Sciences",
        "number": 253,
        "shape": "normal",
        "set": "FOOD",
        "position": ""
    },
    {
        "card_name": "CL04 \u2014 Phyrexian Passage",
        "number": 254,
        "shape": "normal",
        "set": "FOOD",
        "position": ""
    },
    {
        "card_name": "CL05 \u2014 The Valley Market",
        "number": 255,
        "shape": "normal",
        "set": "FOOD",
        "position": ""
    },
    {
        "card_name": "er"
    },
    {
        "card_name": "er"
    },
    {
        "card_name": "er"
    },
    {
        "card_name": "er"
    },
    {
        "card_name": "er"
    }
]